Workbook

Sheet 안내
A1: 조사 시트 템플릿 v1
A2: 만든 날 | B2: 2026-09-16 · 기획서 docs/PLAN.md, 열 구조 docs/RESEARCH_SHEET.md
A3: 목적 | B3: 프로그램(M0~M1)이 만들어지기 전까지 조사 내용을 같은 구조로 기록한다. M0의 "가져오기"가 이 파일을 그대로 읽는다.
A4: 색 규칙 | B4: 파란 글씨 = 직접 입력하는 칸. 검은 글씨 = 수식(고치지 않음). 노란 배경 헤더 = 원가 계산에 꼭 필요한 입력. 회색 배경 행 = 예시(가상 값, 실제 데이터 아님).
A5: 상태 값 | B5: 확인 = 출처·날짜·캡처가 있음. 추정 = 근거는 있으나 직접 확인 안 함. 미확인 = 모름. 금액 칸이 비어 있으면 미확인으로 취급한다.
A6: 원칙 1 | B6: 모르는 금액을 0으로 적지 않는다. 0은 "0원임을 확인"했을 때만 적고 상태를 확인으로 둔다.
A7: 원칙 2 | B7: 금액은 원래 통화로 적는다. 원화 환산은 원가계산 탭의 환율 칸에서만 한다.
A8: 원칙 3 | B8: 가격·배송 견적은 캡처 파일명이 있어야 확인이다. 링크만 있으면 추정이다.
A9: 원칙 4 | B9: 경쟁사관찰 탭은 참고용이다. 요건 판정이나 가격 결정의 근거로 쓰지 않는다.
A10: 원칙 5 | B10: 결정 탭에는 이유 없는 결정을 적지 않는다.
A11: 원가계산 탭 | B11: 오퍼ID·시나리오ID를 적으면 실결제가·통화·구간 비용·관세를 자동으로 가져온다. 미확인이 하나라도 있으면 결과 칸에 "미확인"이 나온다. 한 계산 행에서는 외화 1종(오퍼 통화)만 가정하며, 모든 구간 비용은 소포당으로 적는다.
A12: ID 규칙 | B12: 상품 P-, 공급처 S-, 오퍼 O-, 시나리오 SC-, 계산 CALC-, 경쟁사 C-, 요건 프로필 R-, 결정 D-, 작업 T-. 예시 행은 -EX1.
A13: 탭 | B13: 상품 · 공급처 · 오퍼 · 배송시나리오 · 원가계산 · 경쟁사관찰 · 요건 · 결정 · 작업 · 환율 · 비용항목
A14: 출처 | B14: 초기 값의 출처는 docs/SEED_RESEARCH.md 10장. 예시 행(회색)의 숫자는 형식을 보여 주기 위한 가상 값이다.

Sheet 상품
A1: 상품ID | B1: 상품명 | C1: 캐릭터 | D1: 카테고리 | E1: 옵션방식 | F1: 연령표시 | G1: 상태 | H1: 요건프로필ID | I1: 선택오퍼ID | J1: 선택시나리오ID | K1: 결정판매가(KRW) | L1: 결정청구배송비(KRW) | M1: 경쟁사참고URL | N1: 경쟁사가격(KRW) | O1: 경쟁사관찰일 | P1: 메모
A2: P-001 | B2: 브로콜리·채소 핑구 인형 | C2: 핑구 | D2: 봉제인형 | E2: 지정 | G2: 발견 | H2: R-001 | M2: https://solethings.co.kr/product/detail.html?product_no=2417 | N2: 25000 | P2: 경쟁사 가격은 조사일 미상. 재확인 필요
A3: P-002 | B3: 이모션 핑구 랜덤 인형 키링 | C3: 핑구 | D3: 인형 키링 | E3: 랜덤 | G3: 조사 | H3: R-002 | M3: https://solethings.co.kr/product/detail.html?product_no=2415 | N3: 22000 | O3: 2026-09-16 | P3: 소비자가 30,000원 표기. 4개 구매 시 중복 없음
A4: P-003 | B4: 코끼리 핑구 인형 | C4: 핑구 | D4: 봉제인형 | E4: 지정 | G4: 발견 | H4: R-001 | M4: https://solethings.co.kr/product/detail.html?product_no=2411 | N4: 31500 | P4: 조사일 미상
A5: P-004 | B5: 놀이동산 핑구 랜덤 인형 키링 | C5: 핑구 | D5: 인형 키링 | E5: 랜덤 | G5: 발견 | H5: R-002 | M5: https://solethings.co.kr/product/detail.html?product_no=2399 | N5: 22500 | P5: 기본가 16,500 + 필수 옵션 6,000

Sheet 공급처
A1: 공급처ID | B1: 이름 | C1: 현지이름 | D1: 플랫폼 | E1: 판매자유형 | F1: 매장URL | G1: 국가 | H1: 연락수단 | I1: 한국직배송 | J1: 한국직배송상태 | K1: 결제수단 | L1: 신뢰메모 | M1: 마지막연락일
A2: S-001 | B2: MiiTAKI | C2: 米塔集 | D2: 기타 | E2: 미상 | F2: https://tao.hooos.com/goods_xV4mNnJcktqx9zWbZauQWQFAt9-NeRBBoczKyg7OpDhV.html | G2: CN | I2: 미확인 | J2: 미확인 | L2: 집계 페이지 경유. 실제 매장 미확인
A3: S-002 | B3: SHANDMOO | C3: 山莫 | D3: 티몰 | E3: 미상 | F3: https://detail.tmall.com/item.htm?id=1043043512765 | G3: CN | I3: 미확인 | J3: 미확인 | L3: 旗舰店 여부 미확인. 타오바오 로그인 어려움
A4: S-003 | B4: Ruten 판매자 | D4: 루텐 | E4: 일반 | F4: https://www.ruten.com.tw/item/22637588567212/ | G4: TW | I4: 미확인 | J4: 미확인 | L4: 대만. 통화 TWD
A5: S-EX1 | B5: (예시) 가상 판매자 | C5: 示例 | D5: 타오바오 | E5: 인가 | F5: https://example.invalid/shop | G5: CN | H5: 알리왕왕 | I5: 가능 | J5: 추정 | K5: 카드 | L5: 예시 행. 실제 데이터 아님 | M5: 2026-09-01

Sheet 오퍼
A1: 오퍼ID | B1: 상품ID | C1: 공급처ID | D1: 상품URL | E1: 옵션설명 | F1: 옵션종류 | G1: 세트구성 | H1: 랜덤규칙 | I1: 수량구간최소 | J1: 수량구간최대 | K1: MOQ | L1: 통화 | M1: 표시가 | N1: 표시가상태 | O1: 실결제가 | P1: 실결제가상태 | Q1: 배송포함범위 | R1: 중국내배송비 | S1: 중국내배송비상태 | T1: 판매자국제배송비 | U1: 판매자국제배송비상태 | V1: 리드타임일 | W1: 리드타임상태 | X1: 정품근거 | Y1: 출처유형 | Z1: 출처링크 | AA1: 캡처파일명 | AB1: 확인일 | AC1: 재확인기한 | AD1: 오퍼상태 | AE1: 탈락사유 | AF1: 메모
A2: O-001 | B2: P-001 | C2: S-001 | D2: https://tao.hooos.com/goods_xV4mNnJcktqx9zWbZauQWQFAt9-NeRBBoczKyg7OpDhV.html | F2: 단품 | I2: 1 | J2: 1 | L2: CNY | M2: 79 | N2: 추정 | P2: 미확인 | Q2: 미확인 | S2: 미확인 | U2: 미확인 | W2: 미확인 | X2: 미확인 | Y2: url | Z2: https://tao.hooos.com/goods_xV4mNnJcktqx9zWbZauQWQFAt9-NeRBBoczKyg7OpDhV.html | AD2: 후보 | AF2: 집계 페이지 표시값. 캡처 없음
A3: O-002 | B3: P-002 | C3: S-002 | D3: https://tao.hooos.com/goods_aMN803wIotMYYy5vYvHQQeUjty-ejZ00KFz0kgjwXXc9.html | E3: 랜덤 단품 | F3: 랜덤 | I3: 1 | J3: 1 | L3: CNY | M3: 59.9 | N3: 추정 | P3: 미확인 | Q3: 미확인 | S3: 미확인 | U3: 미확인 | W3: 미확인 | X3: 미확인 | Y3: url | Z3: https://tao.hooos.com/goods_aMN803wIotMYYy5vYvHQQeUjty-ejZ00KFz0kgjwXXc9.html | AD3: 후보 | AF3: 집계 페이지 표시값
A4: O-003 | B4: P-002 | C4: S-002 | D4: https://detail.tmall.com/item.htm?id=1043043512765 | F4: 랜덤 | I4: 1 | J4: 1 | L4: CNY | N4: 미확인 | P4: 미확인 | Q4: 미확인 | S4: 미확인 | U4: 미확인 | W4: 미확인 | X4: 미확인 | Y4: url | Z4: https://detail.tmall.com/item.htm?id=1043043512765 | AD4: 후보 | AF4: Tmall 후보. 접근 어려움
A5: O-004 | B5: P-002 | C5: S-003 | D5: https://www.ruten.com.tw/item/22637588567212/ | E5: 단품·세트 혼재 | F5: 단품 | G5: 730~2,350 TWD 범위에 세트 포함 | I5: 1 | J5: 1 | L5: TWD | M5: 730 | N5: 추정 | P5: 미확인 | Q5: 미확인 | S5: 미확인 | U5: 미확인 | W5: 미확인 | X5: 미확인 | Y5: url | Z5: https://www.ruten.com.tw/item/22637588567212/ | AD5: 후보 | AF5: 통화는 TWD로 확인. 단품 최저가로 기록
A6: O-EX1 | B6: P-002 | C6: S-EX1 | D6: https://example.invalid/item/1 | E6: (예시) 랜덤 단품 | F6: 랜덤 | H6: 4개 구매 시 중복 없음 | I6: 1 | J6: 10 | K6: 1 | L6: CNY | M6: 65 | N6: 추정 | O6: 59.9 | P6: 추정 | Q6: 중국내 | R6: 0 | S6: 추정 | U6: 미확인 | V6: 3 | W6: 추정 | X6: 판매자주장 | Y6: 자체추정 | AB6: 2026-09-01 | AC6: 2026-10-01 | AD6: 후보 | AF6: 예시 행. 값은 가상

Sheet 배송시나리오
A1: 시나리오ID | B1: 상품ID | C1: 오퍼ID | D1: 이름 | E1: 경로 | F1: 소포당개수 | G1: 소포당개수상태 | H1: 소포무게g | I1: 소포무게상태 | J1: 구간1 출발→도착 | K1: 구간1 서비스 | L1: 구간1 비용 | M1: 구간1 통화 | N1: 구간1 상태 | O1: 구간1 포함항목 | P1: 구간2 출발→도착 | Q1: 구간2 서비스 | R1: 구간2 비용 | S1: 구간2 통화 | T1: 구간2 상태 | U1: 구간2 포함항목 | V1: 구간3 출발→도착 | W1: 구간3 서비스 | X1: 구간3 비용 | Y1: 구간3 통화 | Z1: 구간3 상태 | AA1: 구간3 포함항목 | AB1: 통관방식 | AC1: 관세(KRW 소포당) | AD1: 관세상태 | AE1: 부가세(KRW 소포당) | AF1: 부가세상태 | AG1: 예상총일수 | AH1: 확인일 | AI1: 출처/캡처 | AJ1: 메모
A2: SC-001 | B2: P-002 | C2: O-002 | D2: 이모션 직배송 | E2: 직배송 | G2: 미확인 | I2: 미확인 | J2: 판매자→한국고객 | K2: 판매자 국제배송 | M2: CNY | N2: 미확인 | AB2: 미확인 | AD2: 미확인 | AF2: 미확인 | AJ2: 판매자 한국 발송 가능 여부부터 확인
A3: SC-002 | B3: P-002 | C3: O-002 | D3: 이모션 배송대행 | E3: 배송대행 | F3: 4 | G3: 추정 | I3: 미확인 | J3: 판매자→대행창고 | K3: 판매자 중국내 배송 | M3: CNY | N3: 미확인 | P3: 대행창고→한국통관 | Q3: (대행업체 미정) | S3: CNY | T3: 미확인 | U3: 국내택배 포함 여부 미확인 | V3: 한국통관→고객 | W3: 국내택배 | Y3: KRW | Z3: 미확인 | AB3: 미확인 | AD3: 미확인 | AF3: 미확인 | AJ3: 소포당 4개는 쏠띵즈 배송비 계단에서 추정
A4: SC-EX1 | B4: P-002 | C4: O-EX1 | D4: (예시) 배송대행 | E4: 배송대행 | F4: 4 | G4: 추정 | H4: 600 | I4: 추정 | J4: 판매자→대행창고 | K4: 판매자 무료배송 | L4: 0 | M4: CNY | N4: 추정 | P4: 대행창고→한국통관 | Q4: (예시) 대행업체 A 1kg 이하 | R4: 45 | S4: CNY | T4: 추정 | U4: 국내택배 | V4: 한국통관→고객 | W4: 국내택배(구간2에 포함) | X4: 0 | Y4: KRW | Z4: 확인 | AA4: 구간2 견적에 포함되어 0 | AB4: 목록통관 | AC4: 0 | AD4: 추정 | AE4: 0 | AF4: 추정 | AG4: 10~15 | AH4: 2026-09-01 | AI4: 예시 | AJ4: 예시 행. 값은 가상

Sheet 원가계산
A1: 계산ID | B1: 상품ID | C1: 오퍼ID | D1: 시나리오ID | E1: 채널 | F1: 계산일 | G1: 환율(외화1→KRW) | H1: 환율날짜 | I1: 환율출처 | J1: 판매가(KRW) | K1: 청구배송비(KRW) | L1: 주문당개수 | M1: 채널판매수수료율 | N1: 결제수수료율 | O1: 수수료 배송비적용 | P1: 해외결제수수료율 | Q1: 검수포장비(KRW 개당) | R1: 반품예비율 | S1: 광고비(KRW 월) | T1: 고정비(KRW 월) | U1: 예상월판매개수 | V1: 메모 | W1: 실결제가(외화) | X1: 실결제가상태 | Y1: 오퍼통화 | Z1: 소포당개수 | AA1: 소포당개수상태 | AB1: 구간1 | AC1: 구간1비용 | AD1: 구간1통화 | AE1: 구간1상태 | AF1: 구간2 | AG1: 구간2비용 | AH1: 구간2통화 | AI1: 구간2상태 | AJ1: 구간3 | AK1: 구간3비용 | AL1: 구간3통화 | AM1: 구간3상태 | AN1: 관세(KRW) | AO1: 관세상태 | AP1: 부가세(KRW) | AQ1: 부가세상태 | AR1: 미확인개수 | AS1: 추정개수 | AT1: 결과상태 | AU1: 개당매입원가(KRW) | AV1: 개당운송원가(KRW) | AW1: 개당착지원가(KRW) | AX1: 개당수입(KRW) | AY1: 개당채널비용(KRW) | AZ1: 개당공헌이익(KRW) | BA1: 마진율 | BB1: 개당순이익추정(KRW) | BC1: 손익분기판매가(KRW)
A2: CALC-001 | B2: P-002 | C2: O-002 | D2: SC-001 | E2: 스마트스토어 | F2: 2026-09-16 | L2: 1 | O2: 예 | V2: 실제 조사 행. 미확인이 많아 결과가 나오지 않는 것이 정상 | W2: =IFERROR(IF(INDEX(오퍼!$O$2:$O$500,MATCH($C2,오퍼!$A$2:$A$500,0))="","",INDEX(오퍼!$O$2:$O$500,MATCH($C2,오퍼!$A$2:$A$500,0))),"") | X2: =IFERROR(IF(INDEX(오퍼!$P$2:$P$500,MATCH($C2,오퍼!$A$2:$A$500,0))="","",INDEX(오퍼!$P$2:$P$500,MATCH($C2,오퍼!$A$2:$A$500,0))),"") -> 미확인 | Y2: =IFERROR(IF(INDEX(오퍼!$L$2:$L$500,MATCH($C2,오퍼!$A$2:$A$500,0))="","",INDEX(오퍼!$L$2:$L$500,MATCH($C2,오퍼!$A$2:$A$500,0))),"") -> CNY | Z2: =IFERROR(IF(INDEX(배송시나리오!$F$2:$F$500,MATCH($D2,배송시나리오!$A$2:$A$500,0))="","",INDEX(배송시나리오!$F$2:$F$500,MATCH($D2,배송시나리오!$A$2:$A$500,0))),"") | AA2: =IFERROR(IF(INDEX(배송시나리오!$G$2:$G$500,MATCH($D2,배송시나리오!$A$2:$A$500,0))="","",INDEX(배송시나리오!$G$2:$G$500,MATCH($D2,배송시나리오!$A$2:$A$500,0))),"") -> 미확인 | AB2: =IFERROR(IF(INDEX(배송시나리오!$J$2:$J$500,MATCH($D2,배송시나리오!$A$2:$A$500,0))="","",INDEX(배송시나리오!$J$2:$J$500,MATCH($D2,배송시나리오!$A$2:$A$500,0))),"") -> 판매자→한국고객 | AC2: =IFERROR(IF(INDEX(배송시나리오!$L$2:$L$500,MATCH($D2,배송시나리오!$A$2:$A$500,0))="","",INDEX(배송시나리오!$L$2:$L$500,MATCH($D2,배송시나리오!$A$2:$A$500,0))),"") | AD2: =IFERROR(IF(INDEX(배송시나리오!$M$2:$M$500,MATCH($D2,배송시나리오!$A$2:$A$500,0))="","",INDEX(배송시나리오!$M$2:$M$500,MATCH($D2,배송시나리오!$A$2:$A$500,0))),"") -> CNY | AE2: =IFERROR(IF(INDEX(배송시나리오!$N$2:$N$500,MATCH($D2,배송시나리오!$A$2:$A$500,0))="","",INDEX(배송시나리오!$N$2:$N$500,MATCH($D2,배송시나리오!$A$2:$A$500,0))),"") -> 미확인 | AF2: =IFERROR(IF(INDEX(배송시나리오!$P$2:$P$500,MATCH($D2,배송시나리오!$A$2:$A$500,0))="","",INDEX(배송시나리오!$P$2:$P$500,MATCH($D2,배송시나리오!$A$2:$A$500,0))),"") | AG2: =IFERROR(IF(INDEX(배송시나리오!$R$2:$R$500,MATCH($D2,배송시나리오!$A$2:$A$500,0))="","",INDEX(배송시나리오!$R$2:$R$500,MATCH($D2,배송시나리오!$A$2:$A$500,0))),"") | AH2: =IFERROR(IF(INDEX(배송시나리오!$S$2:$S$500,MATCH($D2,배송시나리오!$A$2:$A$500,0))="","",INDEX(배송시나리오!$S$2:$S$500,MATCH($D2,배송시나리오!$A$2:$A$500,0))),"") | AI2: =IFERROR(IF(INDEX(배송시나리오!$T$2:$T$500,MATCH($D2,배송시나리오!$A$2:$A$500,0))="","",INDEX(배송시나리오!$T$2:$T$500,MATCH($D2,배송시나리오!$A$2:$A$500,0))),"") | AJ2: =IFERROR(IF(INDEX(배송시나리오!$V$2:$V$500,MATCH($D2,배송시나리오!$A$2:$A$500,0))="","",INDEX(배송시나리오!$V$2:$V$500,MATCH($D2,배송시나리오!$A$2:$A$500,0))),"") | AK2: =IFERROR(IF(INDEX(배송시나리오!$X$2:$X$500,MATCH($D2,배송시나리오!$A$2:$A$500,0))="","",INDEX(배송시나리오!$X$2:$X$500,MATCH($D2,배송시나리오!$A$2:$A$500,0))),"") | AL2: =IFERROR(IF(INDEX(배송시나리오!$Y$2:$Y$500,MATCH($D2,배송시나리오!$A$2:$A$500,0))="","",INDEX(배송시나리오!$Y$2:$Y$500,MATCH($D2,배송시나리오!$A$2:$A$500,0))),"") | AM2: =IFERROR(IF(INDEX(배송시나리오!$Z$2:$Z$500,MATCH($D2,배송시나리오!$A$2:$A$500,0))="","",INDEX(배송시나리오!$Z$2:$Z$500,MATCH($D2,배송시나리오!$A$2:$A$500,0))),"") | AN2: =IFERROR(IF(INDEX(배송시나리오!$AC$2:$AC$500,MATCH($D2,배송시나리오!$A$2:$A$500,0))="","",INDEX(배송시나리오!$AC$2:$AC$500,MATCH($D2,배송시나리오!$A$2:$A$500,0))),"") | AO2: =IFERROR(IF(INDEX(배송시나리오!$AD$2:$AD$500,MATCH($D2,배송시나리오!$A$2:$A$500,0))="","",INDEX(배송시나리오!$AD$2:$AD$500,MATCH($D2,배송시나리오!$A$2:$A$500,0))),"") -> 미확인 | AP2: =IFERROR(IF(INDEX(배송시나리오!$AE$2:$AE$500,MATCH($D2,배송시나리오!$A$2:$A$500,0))="","",INDEX(배송시나리오!$AE$2:$AE$500,MATCH($D2,배송시나리오!$A$2:$A$500,0))),"") | AQ2: =IFERROR(IF(INDEX(배송시나리오!$AF$2:$AF$500,MATCH($D2,배송시나리오!$A$2:$A$500,0))="","",INDEX(배송시나리오!$AF$2:$AF$500,MATCH($D2,배송시나리오!$A$2:$A$500,0))),"") -> 미확인 | AR2: =IF(OR($W2="",$X2="미확인"),1,0)+IF($G2="",1,0)+IF($J2="",1,0)+IF($K2="",1,0)+IF(OR($L2="",$L2=0),1,0)+IF($M2="",1,0)+IF($N2="",1,0)+IF($P2="",1,0)+IF($Q2="",1,0)+IF($R2="",1,0)+IF(OR($Z2="",$Z2=0,$AA2="미확인"),1,0)+IF($AB2="",0,IF(OR($AC2="",$AE2="미확인"),1,0))+IF($AF2="",0,IF(OR($AG2="",$AI2="미확인"),1,0))+IF($AJ2="",0,IF(OR($AK2="",$AM2="미확인"),1,0))+IF(OR($AN2="",$AO2="미확인"),1,0)+IF(OR($AP2="",$AQ2="미확인"),1,0) -> 13 | AS2: =COUNTIF($X2,"추정")+COUNTIF($AA2,"추정")+COUNTIF($AE2,"추정")+COUNTIF($AI2,"추정")+COUNTIF($AM2,"추정")+COUNTIF($AO2,"추정")+COUNTIF($AQ2,"추정") -> 0 | AT2: =IF($AR2>0,"미확인 "&$AR2&"개",IF($AS2>0,"추정 포함","확인")) -> 미확인 13개 | AU2: =IF($AR2>0,"미확인",$W2*IF($Y2="KRW",1,$G2)*(1+$P2)) -> 미확인 | AV2: =IF($AR2>0,"미확인",(IF($AB2="",0,$AC2*IF($AD2="KRW",1,$G2))+IF($AF2="",0,$AG2*IF($AH2="KRW",1,$G2))+IF($AJ2="",0,$AK2*IF($AL2="KRW",1,$G2))+$AN2+$AP2)/$Z2) -> 미확인 | AW2: =IF($AR2>0,"미확인",$AU2+$AV2+$Q2) -> 미확인 | AX2: =IF($AR2>0,"미확인",$J2+$K2/$L2) -> 미확인 | AY2: =IF($AR2>0,"미확인",($J2+IF($O2="예",$K2/$L2,0))*($M2+$N2)) -> 미확인 | AZ2: =IF($AR2>0,"미확인",$AX2-$AW2-$AY2-$J2*$R2) -> 미확인 | BA2: =IF($AR2>0,"미확인",IF($AX2=0,"미확인",$AZ2/$AX2)) -> 미확인 | BB2: =IF($AR2>0,"미확인",IF(OR($S2="",$T2="",$U2="",$U2=0),"미확인",$AZ2-($S2+$T2)/$U2)) -> 미확인 | BC2: =IF($AR2>0,"미확인",IF((1-$M2-$N2-$R2)<=0,"미확인",($AW2+IF($O2="예",$K2/$L2,0)*($M2+$N2)-$K2/$L2)/(1-$M2-$N2-$R2))) -> 미확인
A3: CALC-002 | B3: P-002 | C3: O-002 | D3: SC-002 | E3: 스마트스토어 | F3: 2026-09-16 | L3: 1 | O3: 예 | V3: 실제 조사 행 | W3: =IFERROR(IF(INDEX(오퍼!$O$2:$O$500,MATCH($C3,오퍼!$A$2:$A$500,0))="","",INDEX(오퍼!$O$2:$O$500,MATCH($C3,오퍼!$A$2:$A$500,0))),"") | X3: =IFERROR(IF(INDEX(오퍼!$P$2:$P$500,MATCH($C3,오퍼!$A$2:$A$500,0))="","",INDEX(오퍼!$P$2:$P$500,MATCH($C3,오퍼!$A$2:$A$500,0))),"") -> 미확인 | Y3: =IFERROR(IF(INDEX(오퍼!$L$2:$L$500,MATCH($C3,오퍼!$A$2:$A$500,0))="","",INDEX(오퍼!$L$2:$L$500,MATCH($C3,오퍼!$A$2:$A$500,0))),"") -> CNY | Z3: =IFERROR(IF(INDEX(배송시나리오!$F$2:$F$500,MATCH($D3,배송시나리오!$A$2:$A$500,0))="","",INDEX(배송시나리오!$F$2:$F$500,MATCH($D3,배송시나리오!$A$2:$A$500,0))),"") -> 4 | AA3: =IFERROR(IF(INDEX(배송시나리오!$G$2:$G$500,MATCH($D3,배송시나리오!$A$2:$A$500,0))="","",INDEX(배송시나리오!$G$2:$G$500,MATCH($D3,배송시나리오!$A$2:$A$500,0))),"") -> 추정 | AB3: =IFERROR(IF(INDEX(배송시나리오!$J$2:$J$500,MATCH($D3,배송시나리오!$A$2:$A$500,0))="","",INDEX(배송시나리오!$J$2:$J$500,MATCH($D3,배송시나리오!$A$2:$A$500,0))),"") -> 판매자→대행창고 | AC3: =IFERROR(IF(INDEX(배송시나리오!$L$2:$L$500,MATCH($D3,배송시나리오!$A$2:$A$500,0))="","",INDEX(배송시나리오!$L$2:$L$500,MATCH($D3,배송시나리오!$A$2:$A$500,0))),"") | AD3: =IFERROR(IF(INDEX(배송시나리오!$M$2:$M$500,MATCH($D3,배송시나리오!$A$2:$A$500,0))="","",INDEX(배송시나리오!$M$2:$M$500,MATCH($D3,배송시나리오!$A$2:$A$500,0))),"") -> CNY | AE3: =IFERROR(IF(INDEX(배송시나리오!$N$2:$N$500,MATCH($D3,배송시나리오!$A$2:$A$500,0))="","",INDEX(배송시나리오!$N$2:$N$500,MATCH($D3,배송시나리오!$A$2:$A$500,0))),"") -> 미확인 | AF3: =IFERROR(IF(INDEX(배송시나리오!$P$2:$P$500,MATCH($D3,배송시나리오!$A$2:$A$500,0))="","",INDEX(배송시나리오!$P$2:$P$500,MATCH($D3,배송시나리오!$A$2:$A$500,0))),"") -> 대행창고→한국통관 | AG3: =IFERROR(IF(INDEX(배송시나리오!$R$2:$R$500,MATCH($D3,배송시나리오!$A$2:$A$500,0))="","",INDEX(배송시나리오!$R$2:$R$500,MATCH($D3,배송시나리오!$A$2:$A$500,0))),"") | AH3: =IFERROR(IF(INDEX(배송시나리오!$S$2:$S$500,MATCH($D3,배송시나리오!$A$2:$A$500,0))="","",INDEX(배송시나리오!$S$2:$S$500,MATCH($D3,배송시나리오!$A$2:$A$500,0))),"") -> CNY | AI3: =IFERROR(IF(INDEX(배송시나리오!$T$2:$T$500,MATCH($D3,배송시나리오!$A$2:$A$500,0))="","",INDEX(배송시나리오!$T$2:$T$500,MATCH($D3,배송시나리오!$A$2:$A$500,0))),"") -> 미확인 | AJ3: =IFERROR(IF(INDEX(배송시나리오!$V$2:$V$500,MATCH($D3,배송시나리오!$A$2:$A$500,0))="","",INDEX(배송시나리오!$V$2:$V$500,MATCH($D3,배송시나리오!$A$2:$A$500,0))),"") -> 한국통관→고객 | AK3: =IFERROR(IF(INDEX(배송시나리오!$X$2:$X$500,MATCH($D3,배송시나리오!$A$2:$A$500,0))="","",INDEX(배송시나리오!$X$2:$X$500,MATCH($D3,배송시나리오!$A$2:$A$500,0))),"") | AL3: =IFERROR(IF(INDEX(배송시나리오!$Y$2:$Y$500,MATCH($D3,배송시나리오!$A$2:$A$500,0))="","",INDEX(배송시나리오!$Y$2:$Y$500,MATCH($D3,배송시나리오!$A$2:$A$500,0))),"") -> KRW | AM3: =IFERROR(IF(INDEX(배송시나리오!$Z$2:$Z$500,MATCH($D3,배송시나리오!$A$2:$A$500,0))="","",INDEX(배송시나리오!$Z$2:$Z$500,MATCH($D3,배송시나리오!$A$2:$A$500,0))),"") -> 미확인 | AN3: =IFERROR(IF(INDEX(배송시나리오!$AC$2:$AC$500,MATCH($D3,배송시나리오!$A$2:$A$500,0))="","",INDEX(배송시나리오!$AC$2:$AC$500,MATCH($D3,배송시나리오!$A$2:$A$500,0))),"") | AO3: =IFERROR(IF(INDEX(배송시나리오!$AD$2:$AD$500,MATCH($D3,배송시나리오!$A$2:$A$500,0))="","",INDEX(배송시나리오!$AD$2:$AD$500,MATCH($D3,배송시나리오!$A$2:$A$500,0))),"") -> 미확인 | AP3: =IFERROR(IF(INDEX(배송시나리오!$AE$2:$AE$500,MATCH($D3,배송시나리오!$A$2:$A$500,0))="","",INDEX(배송시나리오!$AE$2:$AE$500,MATCH($D3,배송시나리오!$A$2:$A$500,0))),"") | AQ3: =IFERROR(IF(INDEX(배송시나리오!$AF$2:$AF$500,MATCH($D3,배송시나리오!$A$2:$A$500,0))="","",INDEX(배송시나리오!$AF$2:$AF$500,MATCH($D3,배송시나리오!$A$2:$A$500,0))),"") -> 미확인 | AR3: =IF(OR($W3="",$X3="미확인"),1,0)+IF($G3="",1,0)+IF($J3="",1,0)+IF($K3="",1,0)+IF(OR($L3="",$L3=0),1,0)+IF($M3="",1,0)+IF($N3="",1,0)+IF($P3="",1,0)+IF($Q3="",1,0)+IF($R3="",1,0)+IF(OR($Z3="",$Z3=0,$AA3="미확인"),1,0)+IF($AB3="",0,IF(OR($AC3="",$AE3="미확인"),1,0))+IF($AF3="",0,IF(OR($AG3="",$AI3="미확인"),1,0))+IF($AJ3="",0,IF(OR($AK3="",$AM3="미확인"),1,0))+IF(OR($AN3="",$AO3="미확인"),1,0)+IF(OR($AP3="",$AQ3="미확인"),1,0) -> 14 | AS3: =COUNTIF($X3,"추정")+COUNTIF($AA3,"추정")+COUNTIF($AE3,"추정")+COUNTIF($AI3,"추정")+COUNTIF($AM3,"추정")+COUNTIF($AO3,"추정")+COUNTIF($AQ3,"추정") -> 1 | AT3: =IF($AR3>0,"미확인 "&$AR3&"개",IF($AS3>0,"추정 포함","확인")) -> 미확인 14개 | AU3: =IF($AR3>0,"미확인",$W3*IF($Y3="KRW",1,$G3)*(1+$P3)) -> 미확인 | AV3: =IF($AR3>0,"미확인",(IF($AB3="",0,$AC3*IF($AD3="KRW",1,$G3))+IF($AF3="",0,$AG3*IF($AH3="KRW",1,$G3))+IF($AJ3="",0,$AK3*IF($AL3="KRW",1,$G3))+$AN3+$AP3)/$Z3) -> 미확인 | AW3: =IF($AR3>0,"미확인",$AU3+$AV3+$Q3) -> 미확인 | AX3: =IF($AR3>0,"미확인",$J3+$K3/$L3) -> 미확인 | AY3: =IF($AR3>0,"미확인",($J3+IF($O3="예",$K3/$L3,0))*($M3+$N3)) -> 미확인 | AZ3: =IF($AR3>0,"미확인",$AX3-$AW3-$AY3-$J3*$R3) -> 미확인 | BA3: =IF($AR3>0,"미확인",IF($AX3=0,"미확인",$AZ3/$AX3)) -> 미확인 | BB3: =IF($AR3>0,"미확인",IF(OR($S3="",$T3="",$U3="",$U3=0),"미확인",$AZ3-($S3+$T3)/$U3)) -> 미확인 | BC3: =IF($AR3>0,"미확인",IF((1-$M3-$N3-$R3)<=0,"미확인",($AW3+IF($O3="예",$K3/$L3,0)*($M3+$N3)-$K3/$L3)/(1-$M3-$N3-$R3))) -> 미확인
A4: CALC-EX1 | B4: P-002 | C4: O-EX1 | D4: SC-EX1 | E4: 스마트스토어 | F4: 2026-09-01 | G4: 195 | H4: 2026-09-01 | I4: (예시) 은행 고시 | J4: 22000 | K4: 5000 | L4: 1 | M4: 0.055 | N4: 0.033 | O4: 예 | P4: 0.02 | Q4: 500 | R4: 0.03 | S4: 100000 | T4: 30000 | U4: 50 | V4: 예시 행. 모든 값은 가상이며 형식만 보여 준다 | W4: =IFERROR(IF(INDEX(오퍼!$O$2:$O$500,MATCH($C4,오퍼!$A$2:$A$500,0))="","",INDEX(오퍼!$O$2:$O$500,MATCH($C4,오퍼!$A$2:$A$500,0))),"") -> 59.9 | X4: =IFERROR(IF(INDEX(오퍼!$P$2:$P$500,MATCH($C4,오퍼!$A$2:$A$500,0))="","",INDEX(오퍼!$P$2:$P$500,MATCH($C4,오퍼!$A$2:$A$500,0))),"") -> 추정 | Y4: =IFERROR(IF(INDEX(오퍼!$L$2:$L$500,MATCH($C4,오퍼!$A$2:$A$500,0))="","",INDEX(오퍼!$L$2:$L$500,MATCH($C4,오퍼!$A$2:$A$500,0))),"") -> CNY | Z4: =IFERROR(IF(INDEX(배송시나리오!$F$2:$F$500,MATCH($D4,배송시나리오!$A$2:$A$500,0))="","",INDEX(배송시나리오!$F$2:$F$500,MATCH($D4,배송시나리오!$A$2:$A$500,0))),"") -> 4 | AA4: =IFERROR(IF(INDEX(배송시나리오!$G$2:$G$500,MATCH($D4,배송시나리오!$A$2:$A$500,0))="","",INDEX(배송시나리오!$G$2:$G$500,MATCH($D4,배송시나리오!$A$2:$A$500,0))),"") -> 추정 | AB4: =IFERROR(IF(INDEX(배송시나리오!$J$2:$J$500,MATCH($D4,배송시나리오!$A$2:$A$500,0))="","",INDEX(배송시나리오!$J$2:$J$500,MATCH($D4,배송시나리오!$A$2:$A$500,0))),"") -> 판매자→대행창고 | AC4: =IFERROR(IF(INDEX(배송시나리오!$L$2:$L$500,MATCH($D4,배송시나리오!$A$2:$A$500,0))="","",INDEX(배송시나리오!$L$2:$L$500,MATCH($D4,배송시나리오!$A$2:$A$500,0))),"") -> 0 | AD4: =IFERROR(IF(INDEX(배송시나리오!$M$2:$M$500,MATCH($D4,배송시나리오!$A$2:$A$500,0))="","",INDEX(배송시나리오!$M$2:$M$500,MATCH($D4,배송시나리오!$A$2:$A$500,0))),"") -> CNY | AE4: =IFERROR(IF(INDEX(배송시나리오!$N$2:$N$500,MATCH($D4,배송시나리오!$A$2:$A$500,0))="","",INDEX(배송시나리오!$N$2:$N$500,MATCH($D4,배송시나리오!$A$2:$A$500,0))),"") -> 추정 | AF4: =IFERROR(IF(INDEX(배송시나리오!$P$2:$P$500,MATCH($D4,배송시나리오!$A$2:$A$500,0))="","",INDEX(배송시나리오!$P$2:$P$500,MATCH($D4,배송시나리오!$A$2:$A$500,0))),"") -> 대행창고→한국통관 | AG4: =IFERROR(IF(INDEX(배송시나리오!$R$2:$R$500,MATCH($D4,배송시나리오!$A$2:$A$500,0))="","",INDEX(배송시나리오!$R$2:$R$500,MATCH($D4,배송시나리오!$A$2:$A$500,0))),"") -> 45 | AH4: =IFERROR(IF(INDEX(배송시나리오!$S$2:$S$500,MATCH($D4,배송시나리오!$A$2:$A$500,0))="","",INDEX(배송시나리오!$S$2:$S$500,MATCH($D4,배송시나리오!$A$2:$A$500,0))),"") -> CNY | AI4: =IFERROR(IF(INDEX(배송시나리오!$T$2:$T$500,MATCH($D4,배송시나리오!$A$2:$A$500,0))="","",INDEX(배송시나리오!$T$2:$T$500,MATCH($D4,배송시나리오!$A$2:$A$500,0))),"") -> 추정 | AJ4: =IFERROR(IF(INDEX(배송시나리오!$V$2:$V$500,MATCH($D4,배송시나리오!$A$2:$A$500,0))="","",INDEX(배송시나리오!$V$2:$V$500,MATCH($D4,배송시나리오!$A$2:$A$500,0))),"") -> 한국통관→고객 | AK4: =IFERROR(IF(INDEX(배송시나리오!$X$2:$X$500,MATCH($D4,배송시나리오!$A$2:$A$500,0))="","",INDEX(배송시나리오!$X$2:$X$500,MATCH($D4,배송시나리오!$A$2:$A$500,0))),"") -> 0 | AL4: =IFERROR(IF(INDEX(배송시나리오!$Y$2:$Y$500,MATCH($D4,배송시나리오!$A$2:$A$500,0))="","",INDEX(배송시나리오!$Y$2:$Y$500,MATCH($D4,배송시나리오!$A$2:$A$500,0))),"") -> KRW | AM4: =IFERROR(IF(INDEX(배송시나리오!$Z$2:$Z$500,MATCH($D4,배송시나리오!$A$2:$A$500,0))="","",INDEX(배송시나리오!$Z$2:$Z$500,MATCH($D4,배송시나리오!$A$2:$A$500,0))),"") -> 확인 | AN4: =IFERROR(IF(INDEX(배송시나리오!$AC$2:$AC$500,MATCH($D4,배송시나리오!$A$2:$A$500,0))="","",INDEX(배송시나리오!$AC$2:$AC$500,MATCH($D4,배송시나리오!$A$2:$A$500,0))),"") -> 0 | AO4: =IFERROR(IF(INDEX(배송시나리오!$AD$2:$AD$500,MATCH($D4,배송시나리오!$A$2:$A$500,0))="","",INDEX(배송시나리오!$AD$2:$AD$500,MATCH($D4,배송시나리오!$A$2:$A$500,0))),"") -> 추정 | AP4: =IFERROR(IF(INDEX(배송시나리오!$AE$2:$AE$500,MATCH($D4,배송시나리오!$A$2:$A$500,0))="","",INDEX(배송시나리오!$AE$2:$AE$500,MATCH($D4,배송시나리오!$A$2:$A$500,0))),"") -> 0 | AQ4: =IFERROR(IF(INDEX(배송시나리오!$AF$2:$AF$500,MATCH($D4,배송시나리오!$A$2:$A$500,0))="","",INDEX(배송시나리오!$AF$2:$AF$500,MATCH($D4,배송시나리오!$A$2:$A$500,0))),"") -> 추정 | AR4: =IF(OR($W4="",$X4="미확인"),1,0)+IF($G4="",1,0)+IF($J4="",1,0)+IF($K4="",1,0)+IF(OR($L4="",$L4=0),1,0)+IF($M4="",1,0)+IF($N4="",1,0)+IF($P4="",1,0)+IF($Q4="",1,0)+IF($R4="",1,0)+IF(OR($Z4="",$Z4=0,$AA4="미확인"),1,0)+IF($AB4="",0,IF(OR($AC4="",$AE4="미확인"),1,0))+IF($AF4="",0,IF(OR($AG4="",$AI4="미확인"),1,0))+IF($AJ4="",0,IF(OR($AK4="",$AM4="미확인"),1,0))+IF(OR($AN4="",$AO4="미확인"),1,0)+IF(OR($AP4="",$AQ4="미확인"),1,0) -> 0 | AS4: =COUNTIF($X4,"추정")+COUNTIF($AA4,"추정")+COUNTIF($AE4,"추정")+COUNTIF($AI4,"추정")+COUNTIF($AM4,"추정")+COUNTIF($AO4,"추정")+COUNTIF($AQ4,"추정") -> 6 | AT4: =IF($AR4>0,"미확인 "&$AR4&"개",IF($AS4>0,"추정 포함","확인")) -> 추정 포함 | AU4: =IF($AR4>0,"미확인",$W4*IF($Y4="KRW",1,$G4)*(1+$P4)) -> 11914.11 | AV4: =IF($AR4>0,"미확인",(IF($AB4="",0,$AC4*IF($AD4="KRW",1,$G4))+IF($AF4="",0,$AG4*IF($AH4="KRW",1,$G4))+IF($AJ4="",0,$AK4*IF($AL4="KRW",1,$G4))+$AN4+$AP4)/$Z4) -> 2193.75 | AW4: =IF($AR4>0,"미확인",$AU4+$AV4+$Q4) -> 14607.86 | AX4: =IF($AR4>0,"미확인",$J4+$K4/$L4) -> 27000 | AY4: =IF($AR4>0,"미확인",($J4+IF($O4="예",$K4/$L4,0))*($M4+$N4)) -> 2376 | AZ4: =IF($AR4>0,"미확인",$AX4-$AW4-$AY4-$J4*$R4) -> 9356.14 | BA4: =IF($AR4>0,"미확인",IF($AX4=0,"미확인",$AZ4/$AX4)) -> 0.3465237 | BB4: =IF($AR4>0,"미확인",IF(OR($S4="",$T4="",$U4="",$U4=0),"미확인",$AZ4-($S4+$T4)/$U4)) -> 6756.14 | BC4: =IF($AR4>0,"미확인",IF((1-$M4-$N4-$R4)<=0,"미확인",($AW4+IF($O4="예",$K4/$L4,0)*($M4+$N4)-$K4/$L4)/(1-$M4-$N4-$R4))) -> 11392.132

Sheet 경쟁사관찰
A1: 관찰ID | B1: 경쟁사 | C1: URL | D1: 상품명 | E1: 판매가(KRW) | F1: 소비자가(KRW) | G1: 배송비규칙 | H1: 배송기간 | I1: 옵션·랜덤규칙 | J1: 표기(KC/원산지/수입자) | K1: 관찰일 | L1: 캡처파일명 | M1: 메모
A2: C-001 | B2: 쏠띵즈 | C2: https://solethings.co.kr/product/detail.html?product_no=2415 | D2: 이모션 기분어때 핑구 랜덤인형 키링 | E2: 22000 | F2: 30000 | G2: 1~4개 5,900 / 5~8개 11,800 / 9~12개 17,700 / 13~16개 23,600. 무료배송 없음 | H2: 7~21일, 입금 확인 후 | I2: 랜덤박스 1P, 4개 구매 시 중복 없음 | J2: KC·원산지·수입자·정품 문구 없음 | K2: 2026-09-16 | M2: 해외배송 가능상품 표기. 반품 7일, 반송비 고객 부담. 통관 주체 미확인
A3: C-002 | B3: 쏠띵즈 | C3: https://solethings.co.kr/ | D3: (매장 정보) | K3: 2026-09-16 | M3: 카페24. 통신판매업 2023-서울마포-3037. 정품·라이선스 문구 없음
A4: C-003 | B4: 쏠띵즈 | C4: https://solethings.co.kr/product/detail.html?product_no=2417 | D4: 브로콜리·채소 핑구 인형 | E4: 25000 | M4: 조사일 미상. 재확인 필요
A5: C-004 | B5: 쏠띵즈 | C5: https://solethings.co.kr/product/detail.html?product_no=2411 | D5: 코끼리 핑구 인형 | E5: 31500 | M5: 조사일 미상
A6: C-005 | B6: 쏠띵즈 | C6: https://solethings.co.kr/product/detail.html?product_no=2399 | D6: 놀이동산 핑구 랜덤 인형 키링 | E6: 22500 | I6: 기본가 16,500 + 필수 옵션 6,000 | M6: 조사일 미상

Sheet 요건
A1: 프로필ID | B1: 캐릭터 | C1: 카테고리 | D1: 항목키 | E1: 질문 | F1: 답변 | G1: 상태 | H1: 항목결과 | I1: 조건 | J1: 위험도 | K1: 출처 | L1: 확인일 | M1: 재확인기한
A2: R-001 | B2: 핑구 | C2: 봉제인형 | D2: children_product | E2: 이 카테고리가 어린이제품(만 13세 이하 사용 목적)에 해당하는가 | F2: 미판정. 캐릭터 인형은 해당 판정 가능성 높음 | G2: 미확인 | H2: 미확인 | J2: 높음 | K2: 어린이제품 안전 특별법; 확인 경로: 국가기술표준원·1381 질의
A3: R-001 | B3: 핑구 | C3: 봉제인형 | D3: kc | E3: KC 안전확인 표시가 있는 제품인가, 내가 받을 수 있는가 | F3: 규칙: 어린이제품이면 완구 안전확인 대상. 구매대행도 표시 없는 제품 대행 금지 | G3: 확인 | H3: 미확인 | J3: 높음 | K3: 어린이제품 안전 특별법 제20조 등, 1381 안내 (2026-09-16) | L3: 2026-09-16 | M3: 2027-03-15
A4: R-001 | B4: 핑구 | C4: 봉제인형 | D4: trademark_license | E4: 권리자·국내 라이선시·판매자 정품 근거 | F4: 권리자 Mattel. 중국 브랜드 라이선스 여부 미상 | G4: 미확인 | H4: 미확인 | J4: 높음 | K4: Mattel 브랜드 포트폴리오; KIPRIS 조회 필요
A5: R-001 | B5: 핑구 | C5: 봉제인형 | D5: parallel_import | E5: 진정상품 병행수입 요건 충족 가능성 | F5: 규칙 확인. 국내 전용사용권자 관계 미확인 | G5: 미확인 | H5: 미확인 | J5: 중간 | K5: 대법원 판례 요지·법률 안내
A6: R-001 | B6: 핑구 | C6: 봉제인형 | D6: copyright_import | E6: 저작권법 제124조(침해로 보는 수입)에 해당하는가: 국내 저작권자·라이선시 허락 없는 수입 | F6: 미확인 | G6: 미확인 | H6: 미확인 | J6: 높음 | K6: 변리사·변호사, 한국저작권위원회
A7: R-001 | B7: 핑구 | C7: 봉제인형 | D7: design_right | E7: 국내 등록 디자인과 유사한 형상인가 | F7: 미확인 | G7: 미확인 | H7: 미확인 | J7: 중간 | K7: KIPRIS 디자인 검색
A8: R-001 | B8: 핑구 | C8: 봉제인형 | D8: customs_ip_watch | E8: 권리자가 세관에 지재권 신고를 해 두었는가(통관보류 위험) | F8: 미확인 | G8: 미확인 | H8: 미확인 | J8: 높음 | K8: 관세청 지재권 신고 조회·관세사
A9: R-001 | B9: 핑구 | C9: 봉제인형 | D9: platform_ip_report | E9: 채널 지재권 신고 시 정품 소명 자료를 낼 수 있는가 | F9: 미확인 | G9: 미확인 | H9: 미확인 | J9: 중간 | K9: 네이버 지식재산권보호센터
A10: R-001 | B10: 핑구 | C10: 봉제인형 | D10: listing_assets | E10: 상세페이지 이미지·문구 사용권이 있는가 | F10: 직접 촬영 예정 | G10: 추정 | H10: 조건부 | I10: 판매자·공식 이미지 무단 사용 금지 | J10: 중간 | K10: 자체
A11: R-001 | B11: 핑구 | C11: 봉제인형 | D11: customs | E11: 통관 방식·세율·목록통관 가능 여부 | F11: 미확인 | G11: 미확인 | H11: 미확인 | J11: 중간 | K11: 관세청 고객지원·관세사
A12: R-001 | B12: 핑구 | C12: 봉제인형 | D12: labeling | E12: 원산지·구매대행 고지·랜덤 고지 등 표시 의무 | F12: 구매대행 시 구매대행 표시·개인통관고유부호 안내 필요(규칙 확인) | G12: 확인 | H12: 미확인 | J12: 중간 | K12: 전자상거래법 안내, 채널 정책 | L12: 2026-09-16 | M12: 2027-03-15
A13: R-001 | B13: 핑구 | C13: 봉제인형 | D13: channel_policy | E13: 채널이 이 카테고리·모델을 허용하는가 | F13: 미확인 | G13: 미확인 | H13: 미확인 | J13: 낮음 | K13: 채널 판매자 센터
A14: R-001 | B14: 핑구 | C14: 봉제인형 | D14: return_policy | E14: 청약철회·반품 처리 가능성과 비용 | F14: 청약철회 7일(규칙 확인). 해외 반송 비용 미확인 | G14: 확인 | H14: 미확인 | J14: 중간 | K14: 전자상거래법 | L14: 2026-09-16 | M14: 2027-03-15
A15: R-002 | B15: 핑구 | C15: 인형 키링 | D15: children_product | E15: 이 카테고리가 어린이제품(만 13세 이하 사용 목적)에 해당하는가 | F15: 미판정. 캐릭터 인형은 해당 판정 가능성 높음 | G15: 미확인 | H15: 미확인 | J15: 높음 | K15: 어린이제품 안전 특별법; 확인 경로: 국가기술표준원·1381 질의
A16: R-002 | B16: 핑구 | C16: 인형 키링 | D16: kc | E16: KC 안전확인 표시가 있는 제품인가, 내가 받을 수 있는가 | F16: 규칙: 어린이제품이면 완구 안전확인 대상. 구매대행도 표시 없는 제품 대행 금지 | G16: 확인 | H16: 미확인 | J16: 높음 | K16: 어린이제품 안전 특별법 제20조 등, 1381 안내 (2026-09-16) | L16: 2026-09-16 | M16: 2027-03-15
A17: R-002 | B17: 핑구 | C17: 인형 키링 | D17: trademark_license | E17: 권리자·국내 라이선시·판매자 정품 근거 | F17: 권리자 Mattel. 중국 브랜드 라이선스 여부 미상 | G17: 미확인 | H17: 미확인 | J17: 높음 | K17: Mattel 브랜드 포트폴리오; KIPRIS 조회 필요
A18: R-002 | B18: 핑구 | C18: 인형 키링 | D18: parallel_import | E18: 진정상품 병행수입 요건 충족 가능성 | F18: 규칙 확인. 국내 전용사용권자 관계 미확인 | G18: 미확인 | H18: 미확인 | J18: 중간 | K18: 대법원 판례 요지·법률 안내
A19: R-002 | B19: 핑구 | C19: 인형 키링 | D19: copyright_import | E19: 저작권법 제124조(침해로 보는 수입)에 해당하는가: 국내 저작권자·라이선시 허락 없는 수입 | F19: 미확인 | G19: 미확인 | H19: 미확인 | J19: 높음 | K19: 변리사·변호사, 한국저작권위원회
A20: R-002 | B20: 핑구 | C20: 인형 키링 | D20: design_right | E20: 국내 등록 디자인과 유사한 형상인가 | F20: 미확인 | G20: 미확인 | H20: 미확인 | J20: 중간 | K20: KIPRIS 디자인 검색
A21: R-002 | B21: 핑구 | C21: 인형 키링 | D21: customs_ip_watch | E21: 권리자가 세관에 지재권 신고를 해 두었는가(통관보류 위험) | F21: 미확인 | G21: 미확인 | H21: 미확인 | J21: 높음 | K21: 관세청 지재권 신고 조회·관세사
A22: R-002 | B22: 핑구 | C22: 인형 키링 | D22: platform_ip_report | E22: 채널 지재권 신고 시 정품 소명 자료를 낼 수 있는가 | F22: 미확인 | G22: 미확인 | H22: 미확인 | J22: 중간 | K22: 네이버 지식재산권보호센터
A23: R-002 | B23: 핑구 | C23: 인형 키링 | D23: listing_assets | E23: 상세페이지 이미지·문구 사용권이 있는가 | F23: 직접 촬영 예정 | G23: 추정 | H23: 조건부 | I23: 판매자·공식 이미지 무단 사용 금지 | J23: 중간 | K23: 자체
A24: R-002 | B24: 핑구 | C24: 인형 키링 | D24: customs | E24: 통관 방식·세율·목록통관 가능 여부 | F24: 미확인 | G24: 미확인 | H24: 미확인 | J24: 중간 | K24: 관세청 고객지원·관세사
A25: R-002 | B25: 핑구 | C25: 인형 키링 | D25: labeling | E25: 원산지·구매대행 고지·랜덤 고지 등 표시 의무 | F25: 구매대행 시 구매대행 표시·개인통관고유부호 안내 필요(규칙 확인) | G25: 확인 | H25: 미확인 | J25: 중간 | K25: 전자상거래법 안내, 채널 정책 | L25: 2026-09-16 | M25: 2027-03-15
A26: R-002 | B26: 핑구 | C26: 인형 키링 | D26: channel_policy | E26: 채널이 이 카테고리·모델을 허용하는가 | F26: 미확인 | G26: 미확인 | H26: 미확인 | J26: 낮음 | K26: 채널 판매자 센터
A27: R-002 | B27: 핑구 | C27: 인형 키링 | D27: return_policy | E27: 청약철회·반품 처리 가능성과 비용 | F27: 청약철회 7일(규칙 확인). 해외 반송 비용 미확인 | G27: 확인 | H27: 미확인 | J27: 중간 | K27: 전자상거래법 | L27: 2026-09-16 | M27: 2027-03-15

Sheet 결정
A1: 코드 | B1: 제목 | C1: 맥락 | D1: 결정 | E1: 이유 | F1: 대안 | G1: 결과·영향 | H1: 상태 | I1: 결정일 | J1: 재검토조건
A2: D-01 | B2: 사업 모델 | C2: 구매대행/수입판매/혼합/국내 정식 도매 중 선택. KC·세무·합포장·반품이 달라짐 | F2: 구매대행; 수입판매; 혼합; 국내 정식 도매 | G2: 필수 필드·경고·계산식·증빙 규칙 | H2: 제안 | J2: 게이트 조사 결과
A3: D-02 | B3: 핑구 인형·키링 진행 여부 | C3: G-01 게이트 결과에 따라 | F3: 진행; 수입판매 전환; 다른 캐릭터 | G3: 상품 파이프라인 계속/중단 | H3: 제안 | J3: G-01 결과
A4: D-03 | B4: 첫 판매 채널 | C4: 스마트스토어 vs 카페24 자사몰 vs 쿠팡 | D4: 스마트스토어 먼저. 자사몰은 M5 이후 | E4: 유입·결제·정산 내장, API 개방. 자사몰은 유입을 직접 만들어야 하고 PG 계약 필요 | F4: 카페24 자사몰(쏠띵즈 모델); 쿠팡 | G4: 채널 수수료 모델, 연동 방식 | H4: 채택 | I4: 2026-09-16 | J4: 월 주문 100건 초과 또는 브랜드 팔로워 확보 시 자사몰 검토
A5: D-04 | B5: 물류 경로 기본값 | C5: 직배송 vs 배송대행 | D5: 직배송 기본값. 배송대행은 항상 비교 시나리오로 병기 | E5: 사용자 선호. 단 국제 구간 요금은 어느 경로든 한 번이며 어느 쪽이 싼지는 견적으로만 안다 | F5: 배송대행 기본값 | G5: 기본 시나리오, 대행업체 요율표 | H5: 채택 | I5: 2026-09-16 | J5: 판매자 한국 발송 불가가 잦거나 대행 견적이 더 싸면
A6: D-05 | B6: 기술 스택 | C6: 기존 골격 없음 | D6: Cloudflare Workers + D1 + R2 + Cron + Access, Hono, Drizzle, React/Vite | E6: 사용자 Cloudflare 계정, 서버 관리 없음, 단일 사용자 규모 | F6: Pages Functions; 외부 DB; Next.js | G6: ARCHITECTURE.md | H6: 채택 | I6: 2026-09-16 | J6: D1 한계(용량·동시성)에 닿으면
A7: D-06 | B7: 청구 배송비 정책·개인정보 보관 기간 | F7: 실비 전가; 정액; 무료(가격 포함) | G7: 수입 항목 계산, 삭제 Job | H7: 제안 | J7: M2 전

Sheet 작업
A1: 작업ID | B1: 제목 | C1: 관련ID | D1: 우선순위 | E1: 상태 | F1: 기한 | G1: 막힘사유 | H1: 해제조건 | I1: 재확인일 | J1: 메모
A2: T-001 | B2: D-01 사업 모델 결정 | C2: D-01 | D2: 1 | E2: 막힘 | G2: 사용자 결정 대기 | H2: 사용자가 모델을 고르면 | I2: 2026-09-23
A3: T-002 | B3: R-001/R-002 children_product·kc 판정: 1381 또는 국표원 질의, 회신 첨부 | C3: R-001 | D3: 1 | E3: 막힘 | G3: 기관 회신 대기 | H3: 회신 도착 | I3: 2026-09-30
A4: T-003 | B4: trademark_license: KIPRIS에서 Pingu 상표권자·전용사용권자 확인, 공급처에 授权 자료 요청 | C4: R-001 | D4: 1 | E4: 할일
A5: T-004 | B5: 오퍼 4건 실결제가·옵션·한국 배송 견적 캡처 | C5: O-001 | D5: 2 | E5: 할일 | J5: O-001~O-004
A6: T-005 | B6: 배송대행 업체 후보 2곳 요율표 확보(타오바오 공식 집운 포함) | C6: SC-002 | D6: 2 | E6: 할일
A7: T-006 | B7: 환율 소스 결정, 첫 환율 입력 | D7: 2 | E7: 할일
A8: T-007 | B8: 채널 후보별 수수료·구매대행 허용 정책 캡처 | C8: D-03 | D8: 3 | E8: 할일 | J8: 스마트스토어 우선
A9: T-008 | B9: 기존 엑셀 조사 내용을 이 템플릿으로 옮겨 적기 | D9: 3 | E9: 할일

Sheet 환율
A1: 날짜 | B1: 통화 | C1: 원화환율 | D1: 종류 | E1: 출처 | F1: 메모
B2: CNY | D2: 수동 | E2: (입력 필요) 은행 고시 환율 또는 카드 명세 | F2: 첫 환율을 입력하기 전까지 원가 계산은 미확인

Sheet 비용항목
A1: 코드 | B1: 이름 | C1: 방향 | D1: 단계 | E1: 부담 | F1: 발생단위 | G1: 설명
A2: sale_price | B2: 상품 판매대금 | C2: 수입 | D2: 판매 | E2: 고객 | F2: 개당
A3: customer_shipping_fee | B3: 고객 청구 배송비 | C3: 수입 | D3: 판매 | E3: 고객 | F3: 주문당 | G3: 쏠띵즈 5,900원은 이 항목(경쟁사 참고)
A4: goods_cost | B4: 해외 상품 가격(실결제가) | C4: 지출 | D4: 매입 | E4: 나 | F4: 개당
A5: payment_fx_fee | B5: 해외 결제 수수료·환가료 | C5: 지출 | D5: 매입 | E5: 나 | F5: 판매가의% | G5: 실제로는 결제액의 %
A6: cn_domestic_shipping | B6: 중국 내 배송비(판매자→대행창고) | C6: 지출 | D6: 운송 | E6: 나 | F6: 발주당
A7: intl_shipping | B7: 국제배송비 | C7: 지출 | D7: 운송 | E7: 나 | F7: 소포당 | G7: 무게·부피
A8: forwarder_fee | B8: 대행 수수료·합포장·검수·재포장 | C8: 지출 | D8: 운송 | E8: 나 | F8: 소포당
A9: customs_duty | B9: 관세 | C9: 지출 | D9: 통관 | E9: 모델에따라 | F9: 소포당
A10: customs_vat | B10: 수입 부가세 | C10: 지출 | D10: 통관 | E10: 모델에따라 | F10: 소포당
A11: kr_domestic_shipping | B11: 국내 택배비(국제 견적에 미포함일 때만) | C11: 지출 | D11: 운송 | E11: 나 | F11: 소포당 | G11: 포함이면 0이 아니라 "포함"
A12: channel_commission | B12: 채널 판매 수수료 | C12: 지출 | D12: 채널 | E12: 나 | F12: 판매가의% | G12: 배송비 포함 여부는 채널별 확인
A13: payment_processing_fee | B13: 결제 수수료 | C13: 지출 | D13: 채널 | E13: 나 | F13: 판매가의%
A14: inspection_packaging | B14: 검수·포장 자재 | C14: 지출 | D14: 기타 | E14: 나 | F14: 개당
A15: ads | B15: 광고비 | C15: 지출 | D15: 기타 | E15: 나 | F15: 월 | G15: 배분
A16: returns_reserve | B16: 반품·불량 예비비 | C16: 지출 | D16: 기타 | E16: 나 | F16: 판매가의% | G16: 추정
A17: fixed_costs | B17: 고정비(도메인·호스팅·구독) | C17: 지출 | D17: 기타 | E17: 나 | F17: 월 | G17: 배분
